LICENSE
README.md
setup.cfg
setup.py
bev_toolbox/__init__.py
bev_toolbox/init_toolbox.py
bev_toolbox.egg-info/PKG-INFO
bev_toolbox.egg-info/SOURCES.txt
bev_toolbox.egg-info/dependency_links.txt
bev_toolbox.egg-info/not-zip-safe
bev_toolbox.egg-info/requires.txt
bev_toolbox.egg-info/top_level.txt
bev_toolbox/data_aug/__init__.py
bev_toolbox/data_aug/functional.py
bev_toolbox/data_aug/transforms.py
bev_toolbox/wrapper_mmdet3d/__init__.py
bev_toolbox/wrapper_mmdet3d/data_aug_mmdet3d.py