Metadata-Version: 2.1
Name: bev-toolbox
Version: 0.1
Summary: Toolbox for BEV Perception
Home-page: https://github.com/OpenPerceptionX/BEVPerception-Survey-Recipe
Author: OpenPerceptionX
Author-email: simachonghao@pjlab.org.cn
License: Apache 2.0
Platform: UNKNOWN
Requires-Python: >=3.5
License-File: LICENSE
